AISC/__init__.py
AISC/models.py
AISC/DL/VAE.py
AISC/DL/VAEMC.py
AISC/DL/__init__.py
AISC/FeatureExtractor/BivariateFeatures.py
AISC/FeatureExtractor/FeatureExtractor.py
AISC/FeatureExtractor/SpectralFeatures.py
AISC/FeatureExtractor/TimeDomainFeatures.py
AISC/FeatureExtractor/__init__.py
AISC/WaveDetector/WDet.py
AISC/WaveDetector/__init__.py
AISC/modules/__init__.py
AISC/modules/feature.py
AISC/modules/stats.py
AISC/modules/test/__init__.py
AISC/utils/__init__.py
AISC/utils/cv2_util.py
AISC/utils/feature.py
AISC/utils/files.py
AISC/utils/signal.py
AISC/utils/stats.py
AISC/utils/types.py
AISC/utils/vector.py
annotation_tools/CyberPSG.py
annotation_tools/XML_CVAT.py
annotation_tools/XML_CyberPSG.py
annotation_tools/__init__.py
annotation_tools/xml_structured_parsing/__init__.py
annotation_tools/xml_structured_parsing/myXML.py
cloud_tools/__init__.py
cloud_tools/_db_connection_variables.py
cloud_tools/_mefclient_connection_variables.py
cloud_tools/db.py
cloud_tools/mef.py
data_conversion_tools/__init__.py
data_conversion_tools/data_convertors/NeuralynxAnnotation_to_CyberPSG.py
data_conversion_tools/data_convertors/NeuralynxMEF_to_SignalPlant.py
data_conversion_tools/data_convertors/XltekVideo_to_CyberPSG.py
data_conversion_tools/data_convertors/__init__.py
hypnogram/CyberPSG.py
hypnogram/NSRR.py
hypnogram/__init__.py
hypnogram/analysis.py
hypnogram/io.py
hypnogram/utils.py
hypnogram/visualisation.py
hypnogram/test/__init__.py
hypnogram/test/test_utils.py
mselair_aisc-0.1.4.dist-info/LICENSE
mselair_aisc-0.1.4.dist-info/METADATA
mselair_aisc-0.1.4.dist-info/WHEEL
mselair_aisc-0.1.4.dist-info/top_level.txt
mselair_aisc-0.1.4.dist-info/RECORD
